evalogger/__init__.py
evalogger/color.py
evalogger/logger.py
evalogger-0.1.1.dist-info/LICENSE
evalogger-0.1.1.dist-info/METADATA
evalogger-0.1.1.dist-info/WHEEL
evalogger-0.1.1.dist-info/top_level.txt
evalogger-0.1.1.dist-info/RECORD
