Metadata-Version: 2.1
Name: evalogger
Version: 0.1.1
Summary: Small and simple logging library
Home-page: https://github.com/Tevtongermany/evalogger
Author: Tevtongermany
Author-email: Tevtongermany@femboy.cx
License: Apache License 2.0
Classifier: Programming Language :: Python :: 3
Classifier: License :: OSI Approved :: MIT License
Classifier: Operating System :: OS Independent
License-File: LICENSE
Requires-Dist: aiohttp
Requires-Dist: requests
